{
  "version": "hs2-summer-mix-v1",
  "questions": [
    {
      "id": "en_re_01",
      "subject": "英語",
      "topic": "仮定法",
      "type": "reorder",
      "text": "もし私が君なら、そんなことはしないだろう。（最後にピリオド）",
      "tokens": [
        "I",
        "were",
        "you",
        "would",
        "I",
        "not",
        "do",
        "If",
        "such",
        "a",
        "thing"
      ],
      "answer": [
        7,
        0,
        1,
        2,
        4,
        3,
        5,
        6,
        8,
        9,
        10
      ],
      "difficulty": "normal",
      "gloss": "もし私があなたなら、そのようなことはしないだろう。"
    },
    {
      "id": "en_re_02",
      "subject": "英語",
      "topic": "分詞構文",
      "type": "reorder",
      "text": "天候が許せば、私たちは明日出発します。（最後にピリオド）",
      "tokens": [
        "permitting",
        "we",
        "start",
        "Weather",
        "will",
        "tomorrow"
      ],
      "answer": [
        3,
        0,
        1,
        4,
        2,
        5
      ],
      "difficulty": "hard",
      "gloss": "天候が許せば、私たちは明日出発するつもりだ。"
    },
    {
      "id": "en_re_03",
      "subject": "英語",
      "topic": "関係詞",
      "type": "reorder",
      "text": "彼には3人の息子がいて、その全員が医者になった。（最後にピリオド）",
      "tokens": [
        "sons",
        "became",
        "has",
        "doctors",
        "whom",
        "three",
        "all",
        "He",
        "of"
      ],
      "answer": [
        7,
        2,
        5,
        0,
        6,
        8,
        4,
        1,
        3
      ],
      "difficulty": "normal",
      "gloss": "彼は3人の息子を持ち、彼らの全員が医者になった。"
    },
    {
      "id": "en_re_04",
      "subject": "英語",
      "topic": "比較",
      "type": "reorder",
      "text": "この本はあの本ほど面白くない。（最後にピリオド）",
      "tokens": [
        "This",
        "book",
        "is",
        "not",
        "as",
        "interesting",
        "as",
        "that",
        "one"
      ],
      "answer": [
        0,
        1,
        2,
        3,
        4,
        5,
        6,
        7,
        8
      ],
      "difficulty": "easy",
      "gloss": "この本はあの本ほど面白くない。"
    },
    {
      "id": "en_re_05",
      "subject": "英語",
      "topic": "動名詞",
      "type": "reorder",
      "text": "雨の中を待たせてしまってすみません。（最後にピリオド）",
      "tokens": [
        "you",
        "kept",
        "waiting",
        "in",
        "rain",
        "sorry",
        "I",
        "am",
        "for",
        "having",
        "the"
      ],
      "answer": [
        6,
        7,
        5,
        8,
        9,
        1,
        0,
        2,
        3,
        10,
        4
      ],
      "difficulty": "normal",
      "gloss": "あなたを雨の中で待たせ続けたことを申し訳なく思う。"
    },
    {
      "id": "en_re_06",
      "subject": "英語",
      "topic": "倒置",
      "type": "reorder",
      "text": "家を出るやいなや、雨が降り出した。（最後にピリオド）",
      "tokens": [
        "had",
        "I",
        "left",
        "than",
        "sooner",
        "No",
        "home",
        "it",
        "began",
        "rain",
        "to"
      ],
      "answer": [
        5,
        4,
        0,
        1,
        2,
        6,
        3,
        7,
        8,
        10,
        9
      ],
      "difficulty": "hard",
      "gloss": "私が家を出るとすぐに雨が降り始めた。"
    },
    {
      "id": "en_re_07",
      "subject": "英語",
      "topic": "不定詞",
      "type": "reorder",
      "text": "彼は親切にも駅への道を教えてくれた。（最後にピリオド）",
      "tokens": [
        "me",
        "enough",
        "to",
        "show",
        "kind",
        "was",
        "He",
        "the",
        "way",
        "to",
        "station",
        "the"
      ],
      "answer": [
        6,
        5,
        4,
        1,
        2,
        3,
        0,
        7,
        8,
        9,
        11,
        10
      ],
      "difficulty": "normal",
      "gloss": "彼は親切なことに私に駅への道を教えてくれた。"
    },
    {
      "id": "en_re_08",
      "subject": "英語",
      "topic": "受動態",
      "type": "reorder",
      "text": "彼はみんなに笑われた。（最後にピリオド）",
      "tokens": [
        "was",
        "by",
        "He",
        "at",
        "laughed",
        "everyone"
      ],
      "answer": [
        2,
        0,
        4,
        3,
        1,
        5
      ],
      "difficulty": "easy",
      "gloss": "彼はみんなに笑われた。"
    },
    {
      "id": "en_re_09",
      "subject": "英語",
      "topic": "関係副詞",
      "type": "reorder",
      "text": "こういうわけで彼は学校に遅れたのです。（最後にピリオド）",
      "tokens": [
        "is",
        "late",
        "why",
        "he",
        "for",
        "reason",
        "This",
        "the",
        "was",
        "school"
      ],
      "answer": [
        6,
        0,
        7,
        5,
        2,
        3,
        8,
        1,
        4,
        9
      ],
      "difficulty": "normal",
      "gloss": "これが彼が学校に遅刻した理由だ。"
    },
    {
      "id": "en_re_10",
      "subject": "英語",
      "topic": "使役動詞",
      "type": "reorder",
      "text": "私は彼にその部屋を掃除させた。（最後にピリオド）",
      "tokens": [
        "had",
        "him",
        "I",
        "room",
        "the",
        "clean"
      ],
      "answer": [
        2,
        0,
        1,
        5,
        4,
        3
      ],
      "difficulty": "normal",
      "gloss": "私は彼に部屋を掃除してもらった。"
    },
    {
      "id": "en_re_11",
      "subject": "英語",
      "topic": "仮定法過去完了",
      "type": "reorder",
      "text": "もっと一生懸命勉強していたら、試験に受かっていただろうに。（最後にピリオド）",
      "tokens": [
        "studied",
        "passed",
        "I",
        "had",
        "harder",
        "have",
        "exam",
        "would",
        "the",
        "If",
        "I"
      ],
      "answer": [
        9,
        2,
        3,
        0,
        4,
        10,
        7,
        5,
        1,
        8,
        6
      ],
      "difficulty": "normal",
      "gloss": "もし私がもっと熱心に勉強していたら、試験に合格していただろう。"
    },
    {
      "id": "en_re_12",
      "subject": "英語",
      "topic": "無生物主語",
      "type": "reorder",
      "text": "この道を行けば駅に着きます。（最後にピリオド）",
      "tokens": [
        "to",
        "take",
        "station",
        "road",
        "This",
        "will",
        "you",
        "the"
      ],
      "answer": [
        4,
        3,
        5,
        1,
        6,
        0,
        7,
        2
      ],
      "difficulty": "normal",
      "gloss": "この道はあなたを駅へ連れて行くだろう。"
    },
    {
      "id": "en_re_13",
      "subject": "英語",
      "topic": "知覚動詞",
      "type": "reorder",
      "text": "私は彼が通りを横切るのを見た。（最後にピリオド）",
      "tokens": [
        "cross",
        "saw",
        "him",
        "the",
        "street",
        "I"
      ],
      "answer": [
        5,
        1,
        2,
        0,
        3,
        4
      ],
      "difficulty": "easy",
      "gloss": "私は彼が通りを渡るのを見た。"
    },
    {
      "id": "en_re_14",
      "subject": "英語",
      "topic": "完了形",
      "type": "reorder",
      "text": "彼がここへ引っ越してきてから5年になる。（最後にピリオド）",
      "tokens": [
        "passed",
        "since",
        "years",
        "moved",
        "have",
        "here",
        "Five",
        "he"
      ],
      "answer": [
        6,
        2,
        4,
        0,
        1,
        7,
        3,
        5
      ],
      "difficulty": "hard",
      "gloss": "彼がここに引っ越して以来、5年が経過した。"
    },
    {
      "id": "en_re_15",
      "subject": "英語",
      "topic": "助動詞",
      "type": "reorder",
      "text": "彼がそんな間違いをしたはずがない。（最後にピリオド）",
      "tokens": [
        "have",
        "He",
        "such",
        "mistake",
        "cannot",
        "made",
        "a"
      ],
      "answer": [
        1,
        4,
        0,
        5,
        2,
        6,
        3
      ],
      "difficulty": "normal",
      "gloss": "彼がそのような間違いをしたはずがない。"
    },
    {
      "id": "en_re_16",
      "subject": "英語",
      "topic": "動名詞（慣用表現）",
      "type": "reorder",
      "text": "あなたからの便りを楽しみに待っています。（最後にピリオド）",
      "tokens": [
        "to",
        "am",
        "I",
        "from",
        "looking",
        "hearing",
        "forward",
        "you"
      ],
      "answer": [
        2,
        1,
        4,
        6,
        0,
        5,
        3,
        7
      ],
      "difficulty": "normal",
      "gloss": "私はあなたから連絡が来るのを楽しみにしている。"
    },
    {
      "id": "en_re_17",
      "subject": "英語",
      "topic": "接続詞",
      "type": "reorder",
      "text": "とても疲れていたので、彼は早く寝た。（最後にピリオド）",
      "tokens": [
        "so",
        "he",
        "tired",
        "to",
        "He",
        "bed",
        "was",
        "went",
        "that",
        "early"
      ],
      "answer": [
        4,
        6,
        0,
        2,
        8,
        1,
        7,
        3,
        5,
        9
      ],
      "difficulty": "easy",
      "gloss": "彼はとても疲れていたので、早く寝た。"
    },
    {
      "id": "en_re_18",
      "subject": "英語",
      "topic": "部分否定",
      "type": "reorder",
      "text": "金持ちが必ずしも幸せとは限らない。（最後にピリオド）",
      "tokens": [
        "are",
        "happy",
        "always",
        "The",
        "not",
        "rich"
      ],
      "answer": [
        3,
        5,
        0,
        4,
        2,
        1
      ],
      "difficulty": "normal",
      "gloss": "金持ちの人々がいつも幸せであるとは限らない。"
    },
    {
      "id": "en_re_19",
      "subject": "英語",
      "topic": "群前置詞",
      "type": "reorder",
      "text": "病気のために、彼は欠席した。（最後にピリオド）",
      "tokens": [
        "of",
        "was",
        "absent",
        "illness",
        "his",
        "Because",
        "he"
      ],
      "answer": [
        5,
        0,
        4,
        3,
        6,
        1,
        2
      ],
      "difficulty": "normal",
      "gloss": "彼の病気のせいで、彼は欠席だった。"
    },
    {
      "id": "en_re_20",
      "subject": "英語",
      "topic": "強調構文",
      "type": "reorder",
      "text": "私が昨日公園で会ったのはトムでした。（最後にピリオド）",
      "tokens": [
        "yesterday",
        "that",
        "It",
        "in",
        "park",
        "met",
        "I",
        "Tom",
        "was",
        "the"
      ],
      "answer": [
        2,
        8,
        7,
        1,
        6,
        5,
        3,
        9,
        4,
        0
      ],
      "difficulty": "hard",
      "gloss": "私が昨日公園で会ったのはトムだった。"
    },
    {
      "id": "jp_re_01",
      "subject": "国語",
      "topic": "古文（助動詞）",
      "type": "reorder",
      "text": "次の語句を並べ替えて、意味が通る古文にしなさい。",
      "tokens": [
        "花",
        "咲き",
        "に",
        "けり"
      ],
      "answer": [
        0,
        1,
        2,
        3
      ],
      "difficulty": "easy",
      "gloss": "花が咲いてしまったなあ（完了・詠嘆）"
    },
    {
      "id": "jp_re_02",
      "subject": "国語",
      "topic": "古文（敬語）",
      "type": "reorder",
      "text": "正しい敬語の順序に並べ替えなさい。",
      "tokens": [
        "給ひ",
        "たまは",
        "せ",
        "れ"
      ],
      "answer": [
        2,
        0,
        1,
        3
      ],
      "difficulty": "hard",
      "gloss": "「せ給ひたまはれ」（最高敬語「せ給ふ」の活用。ここでは二重敬語の形として扱う）"
    },
    {
      "id": "jp_re_03",
      "subject": "国語",
      "topic": "漢文（訓読）",
      "type": "reorder",
      "text": "書き下し文の語順になるように並べ替えなさい。（我・人を・愛す）",
      "tokens": [
        "人",
        "愛",
        "我"
      ],
      "answer": [
        2,
        1,
        0
      ],
      "difficulty": "easy",
      "gloss": "SVO構造（我愛人）"
    },
    {
      "id": "jp_re_04",
      "subject": "国語",
      "topic": "古文（係り結び）",
      "type": "reorder",
      "text": "係り結びの法則に従って並べ替えなさい。",
      "tokens": [
        "こそ",
        "なれ",
        "あはれ",
        "山"
      ],
      "answer": [
        3,
        0,
        2,
        1
      ],
      "difficulty": "normal",
      "gloss": "山こそあはれなれ（こそ→已然形）"
    },
    {
      "id": "jp_re_05",
      "subject": "国語",
      "topic": "漢文（否定）",
      "type": "reorder",
      "text": "「人として信無くんばあるべからず」の白文の語順を選べ。",
      "tokens": [
        "無",
        "信",
        "不",
        "可"
      ],
      "answer": [
        0,
        1,
        2,
        3
      ],
      "difficulty": "hard",
      "gloss": "無信不可（信無くんば不可なり）"
    },
    {
      "id": "jp_re_06",
      "subject": "国語",
      "topic": "古文（接続）",
      "type": "reorder",
      "text": "「行かむ」の形になるよう並べ替えなさい。",
      "tokens": [
        "行か",
        "む",
        "。"
      ],
      "answer": [
        0,
        1,
        2
      ],
      "difficulty": "easy",
      "gloss": "四段活用未然形＋推量「む」"
    },
    {
      "id": "jp_re_07",
      "subject": "国語",
      "topic": "現代文（論理）",
      "type": "reorder",
      "text": "文脈が通るように接続詞を補って並べ替えなさい。",
      "tokens": [
        "結論として",
        "まず",
        "次に",
        "問題がある"
      ],
      "answer": [
        3,
        1,
        2,
        0
      ],
      "difficulty": "normal",
      "gloss": "問題提起→順序立て→結論"
    },
    {
      "id": "jp_re_08",
      "subject": "国語",
      "topic": "古文（形容詞）",
      "type": "reorder",
      "text": "「美しかりき」となるよう並べ替えなさい。",
      "tokens": [
        "き",
        "美し",
        "かり"
      ],
      "answer": [
        1,
        2,
        0
      ],
      "difficulty": "normal",
      "gloss": "シク活用連用形（補助活用）＋過去「き」"
    },
    {
      "id": "jp_re_09",
      "subject": "国語",
      "topic": "漢文（使役）",
      "type": "reorder",
      "text": "「人をして行かしむ」の白文の語順を選べ。",
      "tokens": [
        "行",
        "人",
        "使"
      ],
      "answer": [
        2,
        1,
        0
      ],
      "difficulty": "normal",
      "gloss": "使人行（人をして行かしむ）"
    },
    {
      "id": "jp_re_10",
      "subject": "国語",
      "topic": "古文（和歌）",
      "type": "reorder",
      "text": "下の句を完成させなさい。「ひさかたの 光のどけき 春の日に」",
      "tokens": [
        "心",
        "散る",
        "らむ",
        "静",
        "花の",
        "なく"
      ],
      "answer": [
        3,
        0,
        5,
        4,
        1,
        2
      ],
      "difficulty": "normal",
      "gloss": "静心なく花の散るらむ"
    },
    {
      "id": "jp_re_11",
      "subject": "国語",
      "topic": "四字熟語",
      "type": "reorder",
      "text": "意味の通る四字熟語にしなさい。",
      "tokens": [
        "苦",
        "闘",
        "悪",
        "戦"
      ],
      "answer": [
        2,
        3,
        0,
        1
      ],
      "difficulty": "easy",
      "gloss": "悪戦苦闘"
    },
    {
      "id": "jp_re_12",
      "subject": "国語",
      "topic": "古文（打消）",
      "type": "reorder",
      "text": "「読まざりけり」の構成順。",
      "tokens": [
        "ざり",
        "けり",
        "読ま"
      ],
      "answer": [
        2,
        0,
        1
      ],
      "difficulty": "normal",
      "gloss": "未然形＋打消「ず」の連用形＋過去「けり」"
    },
    {
      "id": "jp_re_13",
      "subject": "国語",
      "topic": "漢文（受身）",
      "type": "reorder",
      "text": "「人に笑はる」の白文の語順。",
      "tokens": [
        "笑",
        "見",
        "人"
      ],
      "answer": [
        1,
        0,
        2
      ],
      "difficulty": "hard",
      "gloss": "見笑人（「見」は受身の助字）※於などを使う場合もあるがここでは簡略化"
    },
    {
      "id": "jp_re_14",
      "subject": "国語",
      "topic": "古文（識別）",
      "type": "reorder",
      "text": "「泣きにけり」の品詞分解順序。",
      "tokens": [
        "に",
        "けり",
        "泣き"
      ],
      "answer": [
        2,
        0,
        1
      ],
      "difficulty": "normal",
      "gloss": "連用形＋完了「ぬ」連用形＋過去「けり」"
    },
    {
      "id": "jp_re_15",
      "subject": "国語",
      "topic": "ことわざ",
      "type": "reorder",
      "text": "ことわざを完成させなさい。",
      "tokens": [
        "万事",
        "塞翁",
        "が",
        "人間",
        "馬"
      ],
      "answer": [
        3,
        0,
        1,
        2,
        4
      ],
      "difficulty": "normal",
      "gloss": "人間（じんかん）万事塞翁が馬"
    },
    {
      "id": "jp_re_16",
      "subject": "国語",
      "topic": "古文（推量）",
      "type": "reorder",
      "text": "「あるにちがいない」という意味になるよう並べ替えなさい。",
      "tokens": [
        "めり",
        "なる",
        "ある"
      ],
      "answer": [
        2,
        1,
        0
      ],
      "difficulty": "hard",
      "gloss": "あるなるめり（撥音便で「あんなるめり」となる元の形）"
    },
    {
      "id": "jp_re_17",
      "subject": "国語",
      "topic": "現代文（慣用句）",
      "type": "reorder",
      "text": "慣用句を完成させなさい。",
      "tokens": [
        "を",
        "相好",
        "崩す"
      ],
      "answer": [
        1,
        0,
        2
      ],
      "difficulty": "hard",
      "gloss": "相好を崩す（顔をほころばせて喜ぶ）"
    },
    {
      "id": "jp_re_18",
      "subject": "国語",
      "topic": "漢文（再読文字）",
      "type": "reorder",
      "text": "「未だ来らず」の白文の語順。",
      "tokens": [
        "未",
        "来",
        "。"
      ],
      "answer": [
        0,
        1,
        2
      ],
      "difficulty": "normal",
      "gloss": "未来（未だ来らず・いまだきたらず）"
    },
    {
      "id": "jp_re_19",
      "subject": "国語",
      "topic": "古文（願望）",
      "type": "reorder",
      "text": "「会いたいものだ」の形。",
      "tokens": [
        "し",
        "が",
        "会は",
        "も"
      ],
      "answer": [
        2,
        0,
        3,
        1
      ],
      "difficulty": "normal",
      "gloss": "会はしもが（～たいものだなあ）"
    },
    {
      "id": "jp_re_20",
      "subject": "国語",
      "topic": "文学史",
      "type": "reorder",
      "text": "成立順に並べなさい。",
      "tokens": [
        "古今和歌集",
        "万葉集",
        "新古今和歌集"
      ],
      "answer": [
        1,
        0,
        2
      ],
      "difficulty": "normal",
      "gloss": "万葉集(奈良)→古今(平安初期)→新古今(鎌倉初期)"
    },
    {
      "id": "ma_ch_01",
      "subject": "数学",
      "topic": "三角関数",
      "type": "mcq",
      "text": "$\\theta$ が第2象限の角で、$\\sin\\theta = \\frac{3}{5}$ のとき、$\\cos\\theta$ の値を選べ。",
      "difficulty": "normal",
      "gloss": "第2象限なのでcosは負。計算: √(1 - (3/5)^2) = 4/5 -> -4/5",
      "choices": [
        "4/5",
        "-4/5",
        "3/4",
        "-3/4"
      ],
      "answerIndex": 1
    },
    {
      "id": "ma_ch_02",
      "subject": "数学",
      "topic": "図形と方程式",
      "type": "mcq",
      "text": "点$(1, -2)$を中心とし、半径が$3$の円の方程式を選べ。",
      "difficulty": "easy",
      "gloss": "基本形 (x-a)^2 + (y-b)^2 = r^2",
      "choices": [
        "(x-1)^2 + (y+2)^2 = 3",
        "(x+1)^2 + (y-2)^2 = 9",
        "(x-1)^2 + (y+2)^2 = 9",
        "(x-1)^2 - (y+2)^2 = 9"
      ],
      "answerIndex": 2
    },
    {
      "id": "ma_ch_03",
      "subject": "数学",
      "topic": "指数関数",
      "type": "mcq",
      "text": "$(\\sqrt[3]{2})^6$ の値を求めよ。",
      "difficulty": "easy",
      "gloss": "2^(1/3 * 6) = 2^2 = 4",
      "choices": [
        "2",
        "4",
        "6",
        "8"
      ],
      "answerIndex": 1
    },
    {
      "id": "ma_ch_04",
      "subject": "数学",
      "topic": "対数関数",
      "type": "mcq",
      "text": "$\\log_2 8 + \\log_2 4$ の計算結果を選べ。",
      "difficulty": "easy",
      "gloss": "3 + 2 = 5",
      "choices": [
        "5",
        "6",
        "12",
        "32"
      ],
      "answerIndex": 0
    },
    {
      "id": "ma_ch_05",
      "subject": "数学",
      "topic": "微分法",
      "type": "mcq",
      "text": "関数 $f(x) = x^2 - 4x + 1$ の $x=3$ における微分係数 $f'(3)$ を求めよ。",
      "difficulty": "normal",
      "gloss": "f'(x)=2x-4 なので f'(3)=6-4=2",
      "choices": [
        "1",
        "2",
        "3",
        "-2"
      ],
      "answerIndex": 1
    },
    {
      "id": "ma_ch_06",
      "subject": "数学",
      "topic": "ベクトル",
      "type": "mcq",
      "text": "$\\vec{a}=(2, 1), \\vec{b}=(x, 4)$ が平行であるとき、$x$ の値を選べ。",
      "difficulty": "normal",
      "gloss": "平行条件は成分の比が等しい。2:1 = x:4 -> x=8",
      "choices": [
        "2",
        "4",
        "8",
        "-8"
      ],
      "answerIndex": 2
    },
    {
      "id": "ma_ch_07",
      "subject": "数学",
      "topic": "数列",
      "type": "mcq",
      "text": "等差数列 $3, 7, 11, ...$ の第10項を求めよ。",
      "difficulty": "normal",
      "gloss": "a_n = 3 + (10-1)*4 = 3 + 36 = 39",
      "choices": [
        "39",
        "40",
        "43",
        "37"
      ],
      "answerIndex": 0
    },
    {
      "id": "ma_ch_08",
      "subject": "数学",
      "topic": "三角関数",
      "type": "mcq",
      "text": "$2\\sin^2\\theta + \\cos\\theta - 2 = 0$ ($0 \\le \\theta < 2\\pi$) の解の個数を選べ。",
      "difficulty": "hard",
      "gloss": "cosに統一して解く。2(1-c^2)+c-2=0 -> 2c^2-c=0 -> c(2c-1)=0 より cosθ=0 または 1/2。0≤θ<2π で θ=π/2,3π/2,π/3,5π/3 の4個。",
      "choices": [
        "1個",
        "2個",
        "3個",
        "4個"
      ],
      "answerIndex": 3
    },
    {
      "id": "ma_ch_09",
      "subject": "数学",
      "topic": "積分法",
      "type": "mcq",
      "text": "$\\int_{0}^{3} 2x dx$ の値を求めよ。",
      "difficulty": "normal",
      "gloss": "[x^2]0->3 = 9 - 0 = 9",
      "choices": [
        "3",
        "6",
        "9",
        "18"
      ],
      "answerIndex": 2
    },
    {
      "id": "ma_ch_10",
      "subject": "数学",
      "topic": "高次方程式",
      "type": "mcq",
      "text": "$x^3 - 1 = 0$ の虚数解の一つを $\\omega$ とするとき、$\\omega^2 + \\omega + 1$ の値は？",
      "difficulty": "normal",
      "gloss": "因数分解 (x-1)(x^2+x+1)=0 より、虚数解は後ろの部分の解。",
      "choices": [
        "0",
        "1",
        "-1",
        "i"
      ],
      "answerIndex": 0
    },
    {
      "id": "ma_ch_11",
      "subject": "数学",
      "topic": "対数不等式",
      "type": "mcq",
      "text": "$\\log_2 x < 3$ を満たす $x$ の範囲を選べ。",
      "difficulty": "normal",
      "gloss": "真数条件 x>0 と、x < 2^3",
      "choices": [
        "x < 8",
        "0 < x < 8",
        "x < 9",
        "0 < x < 9"
      ],
      "answerIndex": 1
    },
    {
      "id": "ma_ch_12",
      "subject": "数学",
      "topic": "加法定理",
      "type": "mcq",
      "text": "$\\sin 75^\\circ$ の値は？",
      "difficulty": "normal",
      "gloss": "sin(45+30) = sin45cos30 + cos45sin30",
      "choices": [
        "(\\sqrt{6}-\\sqrt{2})/4",
        "(\\sqrt{6}+\\sqrt{2})/4",
        "(\\sqrt{3}+1)/2",
        "(\\sqrt{2}+1)/2"
      ],
      "answerIndex": 1
    },
    {
      "id": "ma_ch_13",
      "subject": "数学",
      "topic": "円と直線",
      "type": "mcq",
      "text": "円 $x^2+y^2=5$ と直線 $y=2x$ の交点の個数は？",
      "difficulty": "normal",
      "gloss": "代入して x^2 + 4x^2 = 5 -> 5x^2=5 -> x=±1. 2点ある。",
      "choices": [
        "0個",
        "1個",
        "2個",
        "無限個"
      ],
      "answerIndex": 2
    },
    {
      "id": "ma_ch_14",
      "subject": "数学",
      "topic": "軌跡",
      "type": "mcq",
      "text": "2点A(-1,0), B(1,0)からの距離の2乗の和が10となる点Pの軌跡は？",
      "difficulty": "hard",
      "gloss": "計算すると x^2+y^2=4 となり円になる。",
      "choices": [
        "円",
        "楕円",
        "直線",
        "放物線"
      ],
      "answerIndex": 0
    },
    {
      "id": "ma_ch_15",
      "subject": "数学",
      "topic": "ベクトル（内積）",
      "type": "mcq",
      "text": "$\\vec{a}=(1,\\sqrt{3})$ と $\\vec{b}=(1, 0)$ のなす角 $\\theta$ は？",
      "difficulty": "normal",
      "gloss": "内積=1*1=1. |a|=2, |b|=1. cosθ=1/(2*1)=1/2 -> 60度",
      "choices": [
        "30度",
        "45度",
        "60度",
        "90度"
      ],
      "answerIndex": 2
    },
    {
      "id": "ma_ch_16",
      "subject": "数学",
      "topic": "二項定理",
      "type": "mcq",
      "text": "$(x+y)^4$ の展開式における $x^2 y^2$ の係数は？",
      "difficulty": "normal",
      "gloss": "4C2 = 6",
      "choices": [
        "4",
        "6",
        "8",
        "12"
      ],
      "answerIndex": 1
    },
    {
      "id": "ma_ch_17",
      "subject": "数学",
      "topic": "相加相乗平均",
      "type": "mcq",
      "text": "$x > 0$ のとき、$x + \\frac{4}{x}$ の最小値は？",
      "difficulty": "normal",
      "gloss": "2√(x * 4/x) = 2*2 = 4",
      "choices": [
        "2",
        "4",
        "5",
        "8"
      ],
      "answerIndex": 1
    },
    {
      "id": "ma_ch_18",
      "subject": "数学",
      "topic": "数列（Σ計算）",
      "type": "mcq",
      "text": "$\\sum_{k=1}^{n} k$ の公式を選べ。",
      "difficulty": "easy",
      "gloss": "自然数の和の公式",
      "choices": [
        "n(n+1)",
        "1/2 n(n+1)",
        "n^2",
        "1/6 n(n+1)(2n+1)"
      ],
      "answerIndex": 1
    },
    {
      "id": "ma_ch_19",
      "subject": "数学",
      "topic": "点と直線の距離",
      "type": "mcq",
      "text": "原点と直線 $3x - 4y + 10 = 0$ の距離は？",
      "difficulty": "normal",
      "gloss": "|10| / √(3^2 + 4^2) = 10/5 = 2",
      "choices": [
        "1",
        "2",
        "5",
        "10"
      ],
      "answerIndex": 1
    },
    {
      "id": "ma_ch_20",
      "subject": "数学",
      "topic": "三次関数の極値",
      "type": "mcq",
      "text": "$y = x^3 - 3x$ の極小値は？",
      "difficulty": "normal",
      "gloss": "y'=3x^2-3=3(x+1)(x-1). x=1で極小。1-3=-2",
      "choices": [
        "-2",
        "0",
        "2",
        "-1"
      ],
      "answerIndex": 0
    }
  ]
}